smartgrid/data/openei/Readme.md
smartgrid/data/openei/profile_office_annually.npz
smartgrid/data/openei/profile_office_daily.npz
smartgrid/data/openei/profile_residential_annually.npz
smartgrid/data/openei/profile_residential_daily.npz
smartgrid/data/openei/profile_school_annually.npz
smartgrid/data/openei/profile_school_daily.npz
smartgrid/__init__.py
smartgrid/environment.py
smartgrid/make_env.py
smartgrid/world.py
smartgrid/agents/__init__.py
smartgrid/agents/agent.py
smartgrid/agents/data_conversion.py
smartgrid/agents/profile/__init__.py
smartgrid/agents/profile/agent_profile.py
smartgrid/agents/profile/comfort.py
smartgrid/agents/profile/need.py
smartgrid/agents/profile/production.py
smartgrid/observation/__init__.py
smartgrid/observation/global_observation.py
smartgrid/observation/local_observation.py
smartgrid/observation/observation_manager.py
smartgrid/observation/observations.py
smartgrid/rewards/__init__.py
smartgrid/rewards/reward.py
smartgrid/rewards/reward_collection.py
smartgrid/rewards/numeric/__init__.py
smartgrid/rewards/numeric/differentiated/__init__.py
smartgrid/rewards/numeric/differentiated/adaptability.py
smartgrid/rewards/numeric/differentiated/equity.py
smartgrid/rewards/numeric/differentiated/multi_objective_product.py
smartgrid/rewards/numeric/differentiated/multi_objective_sum.py
smartgrid/rewards/numeric/differentiated/over_consumption.py
smartgrid/rewards/numeric/per_agent/__init__.py
smartgrid/rewards/numeric/per_agent/adaptability.py
smartgrid/rewards/numeric/per_agent/comfort.py
smartgrid/rewards/numeric/per_agent/equity.py
smartgrid/rewards/numeric/per_agent/multi_objective_sum.py
smartgrid/rewards/numeric/per_agent/over_consumption.py
smartgrid/util/__init__.py
smartgrid/util/available_energy.py
smartgrid/util/bounded.py
smartgrid/util/equity.py
smartgrid/util/interpolate.py
smartgrid/wrappers/__init__.py
smartgrid/wrappers/reward_aggregator.py
ethical_smart_grid_simulator-0.0.2.dist-info/METADATA
ethical_smart_grid_simulator-0.0.2.dist-info/WHEEL
ethical_smart_grid_simulator-0.0.2.dist-info/licenses/LICENSE.md
ethical_smart_grid_simulator-0.0.2.dist-info/RECORD
