Metadata-Version: 2.1
Name: ethical-smart-grid-simulator
Version: 0.0.2
Summary: A RL environment for learning ethically-aligned behaviours in a Smart Grid simulator.
Project-URL: Source code, https://github.com/ethicsai/ethical-smart-grid
Project-URL: Bug Tracker, https://github.com/ethicsai/ethical-smart-grid/issues
Author: Clément Scheirlinck
Author-email: Rémy Chaput <rchaput.pro@gmail.com>
License: MIT License
License-File: LICENSE.md
Keywords: Gym,Gymnasium,Machine Ethics,Multi-Agent System,OpenAI Gym,Reinforcement Learning,Smart Grid
Classifier: Intended Audience :: Science/Research
Classifier: License :: OSI Approved :: MIT License
Classifier: Operating System :: OS Independent
Classifier: Programming Language :: Python :: 3
Classifier: Topic :: Scientific/Engineering :: Artificial Intelligence
Requires-Python: >=3.7
Requires-Dist: gymnasium>=0.26.3
Requires-Dist: numpy>=1.24.2
Provides-Extra: extra
Requires-Dist: tqdm>=4.61.2; extra == 'extra'
